hive_metastore_client/__init__.py
hive_metastore_client/hive_metastore_client.py
hive_metastore_client/builders/__init__.py
hive_metastore_client/builders/abstract_builder.py
hive_metastore_client/builders/column_builder.py
hive_metastore_client/builders/database_builder.py
hive_metastore_client/builders/partition_builder.py
hive_metastore_client/builders/serde_info_builder.py
hive_metastore_client/builders/storage_descriptor_builder.py
hive_metastore_client/builders/table_builder.py
thrift_files/__init__.py
thrift_files/libraries/__init__.py
thrift_files/libraries/thrift_facebook_service/FacebookService.py
thrift_files/libraries/thrift_facebook_service/__init__.py
thrift_files/libraries/thrift_facebook_service/constants.py
thrift_files/libraries/thrift_facebook_service/ttypes.py
thrift_files/libraries/thrift_hive_metastore_client/ThriftHiveMetastore.py
thrift_files/libraries/thrift_hive_metastore_client/__init__.py
thrift_files/libraries/thrift_hive_metastore_client/constants.py
thrift_files/libraries/thrift_hive_metastore_client/ttypes.py
hive_metastore_client-1.0.9.dist-info/LICENSE
hive_metastore_client-1.0.9.dist-info/METADATA
hive_metastore_client-1.0.9.dist-info/WHEEL
hive_metastore_client-1.0.9.dist-info/top_level.txt
hive_metastore_client-1.0.9.dist-info/RECORD
