Metadata-Version: 2.1
Name: hive_metastore_client
Version: 1.0.9
Summary: A client for connecting and running DDLs on Hive Metastore with Thrift protocol
Home-page: https://github.com/quintoandar/hive-metastore-client
Author: QuintoAndar
License: Copyright
Keywords: hive hive-metastore hive-client hive-metastore-client metastore
Platform: UNKNOWN
Requires-Python: >=3.7, <4
